Workbook
Name bancos: TABELAS!$A$4:$A$53
Name categorias_despesa: TABELAS!$E$4:$E$11
Name categorias_rendimento: TABELAS!$C$4:$C$12
Name sim_nao: TABELAS!$G$4:$G$5

Sheet INICIO
A2: IR EM DIA | C2: PAINEL DA DECLARAÇÃO
A3: organizador de imposto de renda | C3: Resumo do que já foi preenchido. Tudo aqui é calculado a partir das outras abas.
A5: NAVEGAÇÃO | C5: ANO-CALENDÁRIO
A6: =HYPERLINK("#INICIO!C3"," ▸ Painel") -> ▸ Painel | C6: ANO DE REFERÊNCIA DOS LANÇAMENTOS | D6: 2025
A7: =HYPERLINK("#TITULAR!C3"," Titular") -> Titular
A8: =HYPERLINK("#INFORMES!C3"," Informes") -> Informes | C8: RESUMO
A9: =HYPERLINK("#NOTAS!C3"," Rendimentos") -> Rendimentos | C9: TITULAR | D9: =TITULAR!D6 -> MARIA SOUZA DOS SANTOS
A10: =HYPERLINK("#DESPESAS!C3"," Despesas") -> Despesas | C10: CPF | D10: =TITULAR!D7 -> 000.000.000-00
C11: SALDO TOTAL EM CONTAS (31/12) | D11: =INFORMES!D6 -> 20574.02
A12: LINKS RÁPIDOS | C12: RENDIMENTOS LANÇADOS NO ANO | D12: =NOTAS!D6 -> 11050
A13: =HYPERLINK("https://cav.receita.fazenda.gov.br/"," Portal e-CAC") -> Portal e-CAC | C13: DESPESAS DEDUTÍVEIS LANÇADAS | D13: =DESPESAS!D6 -> 1750
A14: =HYPERLINK("https://www.gov.br/receitafederal/pt-br/assuntos/meu-imposto-de-renda"," Meu Imposto de Renda") -> Meu Imposto de Renda | C14: RENDIMENTOS MENOS DEDUÇÕES | D14: =D12-D13 -> 9300 | E14: não é o imposto devido, é só a base organizada
A15: =HYPERLINK("https://www.gov.br/receitafederal/pt-br"," Receita Federal") -> Receita Federal
C16: CONFERÊNCIA DO PREENCHIMENTO
C17: BANCOS INFORMADOS | D17: =COUNTA(INFORMES!D9,INFORMES!D14,INFORMES!D19,INFORMES!D24) -> 3
A18: =HYPERLINK("https://github.com/Richard-456"," por Richard Lopes Bezerra") -> por Richard Lopes Bezerra | C18: LANÇAMENTOS DE RENDIMENTO | D18: =COUNT(NOTAS!E10:E59) -> 5
C19: LANÇAMENTOS DE DESPESA | D19: =COUNT(DESPESAS!E10:E59) -> 3
C20: INFORMES SEM ARQUIVO ANEXADO | D20: =COUNTA(INFORMES!D9,INFORMES!D14,INFORMES!D19,INFORMES!D24)-COUNTA(INFORMES!D11,INFORMES!D16,INFORMES!D21,INFORMES!D26) -> 0 | E20: o ideal é zero antes de declarar
C22: Os dados preenchidos são de exemplo. Apague-os antes de usar com seus próprios números.

Sheet TITULAR
A2: IR EM DIA | C2: 1. DADOS DO TITULAR
A3: organizador de imposto de renda | C3: Preencha os dados da pessoa física. Campos amarelos são de digitação; cinzas são calculados.
A5: NAVEGAÇÃO | C5: IDENTIFICAÇÃO
A6: =HYPERLINK("#INICIO!C3"," Painel") -> Painel | C6: NOME COMPLETO | D6: MARIA SOUZA DOS SANTOS | E6: dado de exemplo
A7: =HYPERLINK("#TITULAR!C3"," ▸ Titular") -> ▸ Titular | C7: CPF | D7: 000.000.000-00 | E7: texto, para não perder o zero à esquerda
A8: =HYPERLINK("#INFORMES!C3"," Informes") -> Informes | C8: DATA DE NASCIMENTO | D8: 1990-05-14
A9: =HYPERLINK("#NOTAS!C3"," Rendimentos") -> Rendimentos | C9: TÍTULO DE ELEITOR | D9: 000000000000
A10: =HYPERLINK("#DESPESAS!C3"," Despesas") -> Despesas | C10: OCUPAÇÃO PRINCIPAL | D10: ASSALARIADO
C11: CÔNJUGE | D11: JOÃO SOUZA DOS SANTOS
A12: LINKS RÁPIDOS
A13: =HYPERLINK("https://cav.receita.fazenda.gov.br/"," Portal e-CAC") -> Portal e-CAC | C13: ENDEREÇO E CONTATO
A14: =HYPERLINK("https://www.gov.br/receitafederal/pt-br/assuntos/meu-imposto-de-renda"," Meu Imposto de Renda") -> Meu Imposto de Renda | C14: ENDEREÇO COMPLETO | D14: Rua das Palmeiras, 180 - Centro - Cambuí/MG
A15: =HYPERLINK("https://www.gov.br/receitafederal/pt-br"," Receita Federal") -> Receita Federal | C15: ENDEREÇO ABREVIADO (60 caracteres) | D15: =IF(LEN(D14)>60,LEFT(D14,60),D14) -> Rua das Palmeiras, 180 - Centro - Cambuí/MG | E15: corta sozinho no limite do programa da Receita
C16: RESTAM (caracteres) | D16: =60-LEN(D15) -> 17
C17: CEP | D17: 37600-000
A18: =HYPERLINK("https://github.com/Richard-456"," por Richard Lopes Bezerra") -> por Richard Lopes Bezerra | C18: TELEFONE | D18: (35) 3431-0000
C19: CELULAR | D19: (35) 99999-0000
C20: E-MAIL | D20: maria.exemplo@email.com
C22: SITUAÇÃO DA DECLARAÇÃO
C23: HOUVE ALTERAÇÃO DESDE A ENTREGA ANTERIOR | D23: SIM
C24: CÔNJUGE ENTRA COMO DEPENDENTE | D24: NÃO
C25: RESIDENTE NO EXTERIOR | D25: NÃO
C26: NÚMERO DE DEPENDENTES | D26: 1

Sheet INFORMES
A2: IR EM DIA | C2: 2. INFORMES DE RENDIMENTOS BANCÁRIOS
A3: organizador de imposto de renda | C3: Saldo de cada conta em 31/12 e o informe que comprova o valor.
A5: NAVEGAÇÃO | C5: TOTAL DECLARADO EM CONTAS
A6: =HYPERLINK("#INICIO!C3"," Painel") -> Painel | C6: SOMA DOS SALDOS INFORMADOS | D6: =SUM(D10,D15,D20,D25) -> 20574.02
A7: =HYPERLINK("#TITULAR!C3"," Titular") -> Titular
A8: =HYPERLINK("#INFORMES!C3"," ▸ Informes") -> ▸ Informes | C8: 1º BANCO
A9: =HYPERLINK("#NOTAS!C3"," Rendimentos") -> Rendimentos | C9: BANCO | D9: 336 - C6 Bank
A10: =HYPERLINK("#DESPESAS!C3"," Despesas") -> Despesas | C10: SALDO EM 31/12 | D10: 5000
C11: ARQUIVO DO INFORME | D11: informe_c6_2025.pdf | E11: nome do PDF guardado na mesma pasta
A12: LINKS RÁPIDOS
A13: =HYPERLINK("https://cav.receita.fazenda.gov.br/"," Portal e-CAC") -> Portal e-CAC | C13: 2º BANCO
A14: =HYPERLINK("https://www.gov.br/receitafederal/pt-br/assuntos/meu-imposto-de-renda"," Meu Imposto de Renda") -> Meu Imposto de Renda | C14: BANCO | D14: 33 - Banco Santander
A15: =HYPERLINK("https://www.gov.br/receitafederal/pt-br"," Receita Federal") -> Receita Federal | C15: SALDO EM 31/12 | D15: 13123.12
C16: ARQUIVO DO INFORME | D16: informe_santander_2025.pdf | E16: nome do PDF guardado na mesma pasta
A18: =HYPERLINK("https://github.com/Richard-456"," por Richard Lopes Bezerra") -> por Richard Lopes Bezerra | C18: 3º BANCO
C19: BANCO | D19: 260 - Nubank
C20: SALDO EM 31/12 | D20: 2450.9
C21: ARQUIVO DO INFORME | D21: informe_nubank_2025.pdf | E21: nome do PDF guardado na mesma pasta
C23: 4º BANCO
C24: BANCO
C25: SALDO EM 31/12
C26: ARQUIVO DO INFORME | E26: nome do PDF guardado na mesma pasta
C28: A lista de bancos vem do intervalo nomeado 'bancos', na aba TABELAS.

Sheet NOTAS
A2: IR EM DIA | C2: 3. RENDIMENTOS RECEBIDOS
A3: organizador de imposto de renda | C3: Todo valor que entrou no ano, mês a mês. Holerite, freela, aluguel, dividendos.
A5: NAVEGAÇÃO | C5: RESUMO DOS RENDIMENTOS
A6: =HYPERLINK("#INICIO!C3"," Painel") -> Painel | C6: TOTAL DO ANO | D6: =SUM(E10:E59) -> 11050 | E6: =COUNT(E10:E59)&" lançamento(s)" -> 5 lançamento(s)
A7: =HYPERLINK("#TITULAR!C3"," Titular") -> Titular
A8: =HYPERLINK("#INFORMES!C3"," Informes") -> Informes
A9: =HYPERLINK("#NOTAS!C3"," ▸ Rendimentos") -> ▸ Rendimentos | C9: DATA | D9: CATEGORIA | E9: VALOR
A10: =HYPERLINK("#DESPESAS!C3"," Despesas") -> Despesas | C10: 2025-01-05 | D10: HOLERITE | E10: 3000
C11: 2025-02-05 | D11: HOLERITE | E11: 3000
A12: LINKS RÁPIDOS | C12: 2025-02-20 | D12: FREELANCE | E12: 850
A13: =HYPERLINK("https://cav.receita.fazenda.gov.br/"," Portal e-CAC") -> Portal e-CAC | C13: 2025-03-05 | D13: HOLERITE | E13: 3000
A14: =HYPERLINK("https://www.gov.br/receitafederal/pt-br/assuntos/meu-imposto-de-renda"," Meu Imposto de Renda") -> Meu Imposto de Renda | C14: 2025-03-28 | D14: ALUGUEL RECEBIDO | E14: 1200
A15: =HYPERLINK("https://www.gov.br/receitafederal/pt-br"," Receita Federal") -> Receita Federal
A18: =HYPERLINK("https://github.com/Richard-456"," por Richard Lopes Bezerra") -> por Richard Lopes Bezerra

Sheet DESPESAS
A2: IR EM DIA | C2: 4. DESPESAS DEDUTÍVEIS
A3: organizador de imposto de renda | C3: Gastos que reduzem a base de cálculo. Guarde o recibo de cada linha.
A5: NAVEGAÇÃO | C5: RESUMO DAS DEDUÇÕES
A6: =HYPERLINK("#INICIO!C3"," Painel") -> Painel | C6: TOTAL DO ANO | D6: =SUM(E10:E59) -> 1750 | E6: =COUNT(E10:E59)&" lançamento(s)" -> 3 lançamento(s)
A7: =HYPERLINK("#TITULAR!C3"," Titular") -> Titular
A8: =HYPERLINK("#INFORMES!C3"," Informes") -> Informes
A9: =HYPERLINK("#NOTAS!C3"," Rendimentos") -> Rendimentos | C9: DATA | D9: CATEGORIA | E9: VALOR
A10: =HYPERLINK("#DESPESAS!C3"," ▸ Despesas") -> ▸ Despesas | C10: 2025-01-18 | D10: PLANO DE SAÚDE | E10: 420
C11: 2025-02-10 | D11: EDUCAÇÃO | E11: 980
A12: LINKS RÁPIDOS | C12: 2025-03-02 | D12: SAÚDE | E12: 350
A13: =HYPERLINK("https://cav.receita.fazenda.gov.br/"," Portal e-CAC") -> Portal e-CAC
A14: =HYPERLINK("https://www.gov.br/receitafederal/pt-br/assuntos/meu-imposto-de-renda"," Meu Imposto de Renda") -> Meu Imposto de Renda
A15: =HYPERLINK("https://www.gov.br/receitafederal/pt-br"," Receita Federal") -> Receita Federal
A18: =HYPERLINK("https://github.com/Richard-456"," por Richard Lopes Bezerra") -> por Richard Lopes Bezerra

Sheet Planilha1

Sheet TABELAS
A1: TABELAS DE APOIO — alimentam as listas de validação de dados
A2: Cada coluna tem um intervalo nomeado com o nome do cabeçalho. É esse nome que a validação usa.
A3: bancos | C3: categorias_rendimento | E3: categorias_despesa | G3: sim_nao
A4: 1 - Banco do Brasil | C4: HOLERITE | E4: SAÚDE | G4: SIM
A5: 102 - XP Investimentos CCTVM S.A. | C5: 13º SALÁRIO | E5: PLANO DE SAÚDE | G5: NÃO
A6: 104 - Caixa Econômica Federal | C6: FÉRIAS | E6: EDUCAÇÃO
A7: 119 - Banco Western Union do Brasil | C7: FREELANCE | E7: PREVIDÊNCIA PRIVADA (PGBL)
A8: 184 - Banco Itaú BBA S.A. | C8: PRÓ-LABORE (CNPJ) | E8: PENSÃO ALIMENTÍCIA
A9: 197 - Stone Pagamentos | C9: ALUGUEL RECEBIDO | E9: DEPENDENTE
A10: 208 - Banco BTG Pactual | C10: DIVIDENDOS | E10: LIVRO-CAIXA
A11: 212 - Banco Original | C11: RENDIMENTO DE APLICAÇÃO | E11: OUTROS
A12: 218 - Banco Bonsucesso | C12: OUTROS
A13: 229 - Banco Cruzeiro do Sul
A14: 237 - Banco Bradesco
A15: 24 - Banco de Pernambuco
A16: 241 - Banco Clássico
A17: 250 - Banco de Crédito e Varejo (BCV)
A18: 260 - Nubank
A19: 29 - Banco do Estado do Rio de Janeiro
A20: 290 - PagBank
A21: 3 - Banco da Amazônia
A22: 33 - Banco Santander
A23: 336 - C6 Bank
A24: 341 - Itaú Unibanco
... A53: 82 - Banco Topázio
